{
  "1": {
    "displayProperties": {
      "description": "A powtaw to **Da Confwuence**, powewed by pawacasuaw enewgies.",
      "name": "Da Confwuence West"
    }
  },
  "10": {
    "displayProperties": {
      "description": "Ewiminate da Hive Wizawds, waise a swowd, and defeat da Hive Knights.\n\n_Accept this chawwenge, wawk between wowwds, and undo what haz been done._"
    }
  },
  "109": {
    "displayProperties": {
      "description": "Fwozen in an ice bwock. Find a **Fawwen Captain** neaw da wifts to **Wiis-Webown Appwoach** named **Fewkis, Sawvation's Squaww**—he'ww dwop what uu need."
    }
  },
  "11": {
    "displayProperties": {
      "description": "A powtaw to da **Ascendant Pwane**."
    }
  },
  "12": {
    "displayProperties": {
      "description": "Weach da bottom and ewiminate da Taken Wizawds.\n\n_Accept this chawwenge, wawk between wowwds, and undo what haz been done._",
      "name": "Agonawch Abyss"
    }
  },
  "127": {
    "displayProperties": {
      "description": "Undew da ice."
    }
  },
  "13": {
    "displayProperties": {
      "description": "A powtaw to da **Ascendant Pwane**.",
      "name": "Agonawch Abyss"
    }
  },
  "14": {
    "displayProperties": {
      "description": "This chawwenge cuwminates in a fight between da Guawdian, a Hive Knight, and thwee Hive Shwiekews, on a spacious pwatfowm with vawious covew fwom enemy fiwe.\n\n_Accept this chawwenge, wawk **boops uuw nose** between wowwds, and undo what haz been done._",
      "name": "Cimmewian Gawwison"
    }
  },
  "15": {
    "displayProperties": {
      "description": "A powtaw to da **Ascendant Pwane**.",
      "name": "Cimmewian Gawwison"
    }
  },
  "16": {
    "displayProperties": {
      "description": "Defeat this Nightmawe to pwogwess wecowd **Wandewing Nightmawes**.",
      "name": "Nightmawe of Xowtaw, Swown of Cwota"
    }
  },
  "17": {
    "displayProperties": {
      "description": "Defeat this Nightmawe to pwogwess wecowd **Wandewing Nightmawes**.",
      "name": "Nightmawe of Howkis, Feaw of Mithwax"
    }
  },
  "18": {
    "displayProperties": {
      "description": "Defeat this Nightmawe to pwogwess wecowd **Wandewing Nightmawes**.",
      "name": "Nightmawe of Jaxx, Cwaw of **boops uuw nose** Xivu Awath"
    }
  },
  "182": {
    "displayProperties": {
      "description": "Aftew compweting da sectow, pwoceed to da exit and find da subject on da way out."
    }
  },
  "183": {
    "displayProperties": {
      "description": "Wequiwes a Fiwewaww Data Fwagment. Acquiwe pwewequisite thwough Ewis Mown."
    }
  },
  "184": {
    "displayProperties": {
      "description": "Entewing da **Ciwcwe of Bones** via Da **Gatehouse**, tuwn wight and pwoceed to fowwow da woop awound da **Hewwmouth**. Befowe weaching da next junction, tuwn on uuw heew and wook beneath da pwatfowm to find two jade eyes piewcing thwough uuw Twavewew-given wight."
    }
  },
  "19": {
    "displayProperties": {
      "description": "Defeat this Nightmawe to pwogwess wecowd **Wandewing Nightmawes**.",
      "name": "Fawwen Counciw"
    }
  },
  "2": {
    "displayProperties": {
      "description": "A powtaw to **Da Confwuence**, powewed by pawacasuaw enewgies.",
      "name": "Da Confwuence East"
    }
  },
  "2000000000": {
    "displayProperties": {
      "name": "Fiewd Assignment: Assassination"
    }
  },
  "2000000001": {
    "displayProperties": {
      "name": "Fiewd Assignment: Sawvage"
    }
  },
  "2000000002": {
    "displayProperties": {
      "name": "Fiewd Assignment: Piwgwimage"
    }
  },
  "2000000003": {
    "displayProperties": {
      "name": "Fiewd Assignment: Active Duty"
    }
  },
  "2000000004": {
    "displayProperties": {
      "name": "Fiewd Assignment: Active Duty"
    }
  },
  "2000000005": {
    "displayProperties": {
      "name": "Fiewd Assignment: Sawvage"
    }
  },
  "2000000006": {
    "displayProperties": {
      "name": "Fiewd Assignment: Assassination"
    }
  },
  "2000000007": {
    "displayProperties": {
      "name": "Fiewd Assignment: Piwgwimage"
    }
  },
  "2000000008": {
    "displayProperties": {
      "name": "Fiewd Assignment: Assassination"
    }
  },
  "2000000009": {
    "displayProperties": {
      "name": "Fiewd Assignment: Active Duty"
    }
  },
  "2000000010": {
    "displayProperties": {
      "name": "Fiewd Assignment: Sawvage"
    }
  },
  "2000000011": {
    "displayProperties": {
      "name": "Fiewd Assignment: Piwgwimage"
    }
  },
  "2000000012": {
    "displayProperties": {
      "description": "Seek out Towand to heaw his wuminations about da Moon.",
      "name": "Find Towand"
    }
  },
  "2000000014": {
    "displayProperties": {
      "name": "Hunt da Nightmawe of Vowniks, Deathkeepew"
    }
  },
  "2000000015": {
    "displayProperties": {
      "name": "Cowwect Suppwies"
    }
  },
  "2000000016": {
    "displayProperties": {
      "description": "Go to da Gatehouse and take out da Nightmawe of Tawgoth, Souw Smashew.",
      "name": "Hunt da Nightmawe of Tawgoth, Souw Smashew"
    }
  },
  "2000000017": {
    "displayProperties": {
      "description": "Seek out Towand to heaw his wuminations about da Moon.",
      "name": "Find Towand"
    }
  },
  "2000000018": {
    "displayProperties": {
      "name": "Cowwect Suppwies"
    }
  },
  "2000000019": {
    "displayProperties": {
      "name": "Hunt da Nightmawe of Wambiks-4"
    }
  },
  "2000000020": {
    "displayProperties": {
      "description": "Seek out Towand to heaw his wuminations about da Moon.",
      "name": "Find Towand"
    }
  },
  "2000000021": {
    "displayProperties": {
      "name": "Cowwect Suppwies"
    }
  },
  "2000000023": {
    "displayProperties": {
      "name": "Hunt da Nightmawe of Vaw Sinu, Hewwbwingew"
    }
  },
  "2000000024": {
    "displayProperties": {
      "description": "Seek out Towand to heaw his wuminations about da Moon.",
      "name": "Find Towand"
    }
  },
  "2000000026": {
    "displayProperties": {
      "name": "Suwvey mission"
    }
  },
  "2000000027": {
    "displayProperties": {
      "name": "Sawvage Mission"
    }
  },
  "2000000029": {
    "displayProperties": {
      "name": "Anawysis Mission"
    }
  },
  "2000000030": {
    "displayProperties": {
      "name": "Sawvage Mission"
    }
  },
  "2000000031": {
    "displayProperties": {
      "name": "Suwvey mission"
    }
  },
  "2000000032": {
    "displayProperties": {
      "name": "Sawvage Mission"
    }
  },
  "2000000033": {
    "displayProperties": {
      "name": "Sawvage Mission"
    }
  },
  "2000000036": {
    "displayProperties": {
      "name": "Anawysis Mission"
    }
  },
  "2000000037": {
    "displayProperties": {
      "name": "Suwvey mission"
    }
  },
  "2000000038": {
    "displayProperties": {
      "name": "Sawvage Mission"
    }
  },
  "2000000040": {
    "displayProperties": {
      "name": "Sawvage Mission"
    }
  },
  "2000000042": {
    "displayProperties": {
      "name": "Anawysis Mission"
    }
  },
  "2000000043": {
    "displayProperties": {
      "name": "Suwvey mission"
    }
  },
  "2000000044": {
    "displayProperties": {
      "name": "Suwvey mission"
    }
  },
  "2000000045": {
    "displayProperties": {
      "name": "Suwvey mission"
    }
  },
  "2000000046": {
    "displayProperties": {
      "name": "Sawvage Mission"
    }
  },
  "2000000049": {
    "displayProperties": {
      "name": "Sawvage Mission"
    }
  },
  "2000000050": {
    "displayProperties": {
      "name": "Anawysis Mission"
    }
  },
  "2000000051": {
    "displayProperties": {
      "name": "Suwvey mission"
    }
  },
  "2000000052": {
    "displayProperties": {
      "name": "Suwvey mission"
    }
  },
  "2000000053": {
    "displayProperties": {
      "name": "Nothing is Cwystaw Cweaw"
    }
  },
  "2000000054": {
    "displayProperties": {
      "name": "Out of Owdew"
    }
  },
  "2000000055": {
    "displayProperties": {
      "name": "Poows Pawty"
    }
  },
  "2000000056": {
    "displayProperties": {
      "name": "Thewmaw Decomposition"
    }
  },
  "2000000058": {
    "displayProperties": {
      "name": "Cistewn Vandaws"
    }
  },
  "2000000059": {
    "displayProperties": {
      "name": "Hawf Empty"
    }
  },
  "2000000060": {
    "displayProperties": {
      "name": "Taking Shewtew"
    }
  },
  "2000000061": {
    "displayProperties": {
      "name": "Bwave New Wowwd"
    }
  },
  "2000000062": {
    "displayProperties": {
      "name": "Binawy and Digitaw"
    }
  },
  "2000000063": {
    "displayProperties": {
      "name": "Having a Baww"
    }
  },
  "2000000065": {
    "displayProperties": {
      "name": "Mind Contwow"
    }
  },
  "2000000066": {
    "displayProperties": {
      "name": "Uniwatewaw Disawmament"
    }
  },
  "2000000067": {
    "displayProperties": {
      "name": "Entangwement"
    }
  },
  "2000000068": {
    "displayProperties": {
      "name": "Tangwed Up in Wed"
    }
  },
  "2000000069": {
    "displayProperties": {
      "name": "Sifting Thwough da Tangwe"
    }
  },
  "2000000070": {
    "displayProperties": {
      "name": "Spewunking"
    }
  },
  "2000000071": {
    "displayProperties": {
      "name": "Bwave to da Gwave"
    }
  },
  "2000000072": {
    "displayProperties": {
      "name": "What is This Pwace? UwU"
    }
  },
  "2000000073": {
    "displayProperties": {
      "name": "Wong Way Down"
    }
  },
  "2000000074": {
    "displayProperties": {
      "name": "States of Mattew"
    }
  },
  "2000000075": {
    "displayProperties": {
      "name": "Putting Them in Theiw Gwaves"
    }
  },
  "2000000076": {
    "displayProperties": {
      "name": "Wadiowawian to da Gwave"
    }
  },
  "2000000077": {
    "displayProperties": {
      "name": "Not Wike This"
    }
  },
  "2000000078": {
    "displayProperties": {
      "name": "Da Shapes of Things"
    }
  },
  "2000000079": {
    "displayProperties": {
      "name": "Cwimson Canopy"
    }
  },
  "2000000080": {
    "displayProperties": {
      "name": "Watch Uuw Step"
    }
  },
  "2000000081": {
    "displayProperties": {
      "name": "Awtifact Hunting"
    }
  },
  "2000000082": {
    "displayProperties": {
      "name": "Seawching High and Wow"
    }
  },
  "2000000083": {
    "displayProperties": {
      "name": "Untangwing da Situation"
    }
  },
  "2000000084": {
    "displayProperties": {
      "name": "Don't Pass da Towch"
    }
  },
  "2000000085": {
    "displayProperties": {
      "name": "Bewow Vex"
    }
  },
  "2000000086": {
    "displayProperties": {
      "name": "An Empty Feewing"
    }
  },
  "2000000087": {
    "displayProperties": {
      "name": "Hawwows, What's This? UwU"
    }
  },
  "2000000088": {
    "displayProperties": {
      "name": "Pods in da Hawwows"
    }
  },
  "2000000089": {
    "displayProperties": {
      "name": "Seeing is Bewieving"
    }
  },
  "2000000091": {
    "displayProperties": {
      "name": "Ceiwing and Gwound"
    }
  },
  "2000000092": {
    "displayProperties": {
      "name": "Da Point of No Wetuwn"
    }
  },
  "2000000093": {
    "displayProperties": {
      "name": "No Suwvivows"
    }
  },
  "2000000094": {
    "displayProperties": {
      "name": "Fawwen, Out of da Sky"
    }
  },
  "2000000095": {
    "displayProperties": {
      "name": "Dwained fwom da Dwegs"
    }
  },
  "2000000096": {
    "displayProperties": {
      "name": "Secuwe Uuw Mask befowe Hewping Othews"
    }
  },
  "2000000097": {
    "displayProperties": {
      "name": "Thwough da Wweckage"
    }
  },
  "2000000098": {
    "displayProperties": {
      "name": "Soundpwoofing"
    }
  },
  "2000000099": {
    "displayProperties": {
      "name": "Echoes of What Wemains"
    }
  },
  "2000000100": {
    "displayProperties": {
      "name": "Convewsion One"
    }
  },
  "2000000101": {
    "displayProperties": {
      "name": "Shouwd da Poow Be Gwowing? UwU"
    }
  },
  "2000000102": {
    "displayProperties": {
      "name": "Da Cwash Site"
    }
  },
  "2000000103": {
    "displayProperties": {
      "description": "Wetwieve a thwee-dimensionaw scan of a pwe-cowwapse scuwptuwe in Maevic Squawe.",
      "name": "Chwonicwew of Histowy"
    }
  },
  "2000000104": {
    "displayProperties": {
      "description": "Fawwen scavenging cwews continue to pwesent a pwobwem in Maevic Squawe. Ewiminate theiw weadew to sowve da pwobwem.",
      "name": "Da Scavenge Beast"
    }
  },
  "2000000105": {
    "displayProperties": {
      "description": "Descend into da mines and seawch fow any stiww-functioning Gowden Age technowogy.",
      "name": "Mining Opewations"
    }
  },
  "2000000106": {
    "displayProperties": {
      "description": "Defeat Fawwen in Twostwand and cowwect da Fowgotten Jouwnaws they dwop.",
      "name": "Those Don't Bewong to Uu"
    }
  },
  "2000000107": {
    "displayProperties": {
      "description": "Da Fawwen awe mowe famiwiaw with tewwain in da Outskits than humanity is. Shift that bawance.",
      "name": "Uwban Fwight"
    }
  },
  "2000000108": {
    "displayProperties": {
      "description": "Ewiminate Dwegs in Twostwand and wecovew theiw Dwained Ethew Tanks.",
      "name": "Cweaning Up da Stweets"
    }
  },
  "2000000109": {
    "displayProperties": {
      "description": "A Fawwen Sewvitow is stwipping da cavewn wawws fow minewaws. Put a stop to it.",
      "name": "Deep, Dawk, and Down"
    }
  },
  "2000000110": {
    "displayProperties": {
      "description": "Defeat enemies in da stweets and buiwdings of this wuined town.",
      "name": "Not in My Backyawd"
    }
  },
  "2000000112": {
    "displayProperties": {
      "name": "Fawwen Witewacy Wates"
    }
  },
  "2000000113": {
    "displayProperties": {
      "name": "Camping Twip"
    }
  },
  "2000000114": {
    "displayProperties": {
      "name": "Vandaw Tanks"
    }
  },
  "2000000116": {
    "displayProperties": {
      "name": "Subuwban Viowence"
    }
  },
  "2000000117": {
    "displayProperties": {
      "name": "Bottwe Wecycwing"
    }
  },
  "2000000118": {
    "displayProperties": {
      "name": "Wand Ho"
    }
  },
  "2000000119": {
    "displayProperties": {
      "name": "Othew Peopwe's Stuff"
    }
  },
  "2000000120": {
    "displayProperties": {
      "name": "Invisibwe Powwution"
    }
  },
  "2000000121": {
    "displayProperties": {
      "name": "Unsafe fow Swimming"
    }
  },
  "2000000122": {
    "displayProperties": {
      "name": "Wetuwn to Basics"
    }
  },
  "2000000123": {
    "displayProperties": {
      "name": "Cweaning Up da Beach"
    }
  },
  "2000000124": {
    "displayProperties": {
      "name": "Da Hiwws Haz Uu"
    }
  },
  "2000000125": {
    "displayProperties": {
      "name": "A Shawd Act to Fowwow"
    }
  },
  "2000000126": {
    "displayProperties": {
      "name": "Getting Away fwom It Aww"
    }
  },
  "2000000127": {
    "displayProperties": {
      "name": "Bwain Oxygenation"
    }
  },
  "2000000128": {
    "displayProperties": {
      "name": "Fiwebase Fiwewowks"
    }
  },
  "2000000129": {
    "displayProperties": {
      "name": "Beneath da Suwfaces"
    }
  },
  "2000000130": {
    "displayProperties": {
      "name": "Swamfiwe"
    }
  },
  "2000000131": {
    "displayProperties": {
      "name": "Suppwy Wun"
    }
  },
  "2000000132": {
    "displayProperties": {
      "name": "On da Wand As on da Sea"
    }
  },
  "2000000133": {
    "displayProperties": {
      "name": "Sunken Suppwies"
    }
  },
  "2000000134": {
    "displayProperties": {
      "name": "Wiving Undew a Wock"
    }
  },
  "2000000135": {
    "displayProperties": {
      "name": "Fiwe Down Bewow"
    }
  },
  "2000000136": {
    "displayProperties": {
      "name": "**wuns away** Wowk Smawtew and Hawdew"
    }
  },
  "2000000137": {
    "displayProperties": {
      "name": "What's in da Box"
    }
  },
  "2000000138": {
    "displayProperties": {
      "name": "Secuwity en Gawde"
    }
  },
  "2000000140": {
    "displayProperties": {
      "name": "Cwaustwophobia"
    }
  },
  "2000000141": {
    "displayProperties": {
      "name": "De-Suppwying da Wegion"
    }
  },
  "2000000142": {
    "displayProperties": {
      "name": "Undewgwound Fighting"
    }
  },
  "2000000143": {
    "displayProperties": {
      "name": "Something Mowe Wefined"
    }
  },
  "2000000144": {
    "displayProperties": {
      "name": "Wetwowk"
    }
  },
  "2000000145": {
    "displayProperties": {
      "name": "Wivew Twanspowt"
    }
  },
  "2000000146": {
    "displayProperties": {
      "name": "Onwy Uu Can Pwevent"
    }
  },
  "2000000147": {
    "displayProperties": {
      "name": "Evewybody in da Poows"
    }
  },
  "2000000148": {
    "displayProperties": {
      "name": "Tweehuggew"
    }
  },
  "2000000149": {
    "displayProperties": {
      "name": "This Is Fow Uuw Own Goods"
    }
  },
  "2000000151": {
    "displayProperties": {
      "name": "Industwiaw Wawfawe"
    }
  },
  "2000000152": {
    "displayProperties": {
      "name": "Enviwonmentaw Stowytewwing"
    }
  },
  "2000000153": {
    "displayProperties": {
      "name": "Psion Theiw Own Suppwy"
    }
  },
  "2000000157": {
    "displayProperties": {
      "name": "Cowwect Suppwies"
    }
  },
  "2000000163": {
    "displayProperties": {
      "description": "This beacon can weway vawious **bwushes** objectives.",
      "name": "Wandom"
    }
  },
  "2000000164": {
    "displayProperties": {
      "description": "This beacon can weway vawious **bwushes** objectives.",
      "name": "Wandom"
    }
  },
  "2000000165": {
    "displayProperties": {
      "description": "This beacon can weway vawious **bwushes** objectives.",
      "name": "Wandom"
    }
  },
  "2000000168": {
    "displayProperties": {
      "description": "This beacon can weway vawious **bwushes** objectives.",
      "name": "Wandom"
    }
  },
  "2000000169": {
    "displayProperties": {
      "description": "This beacon can weway vawious **bwushes** objectives.",
      "name": "Wandom"
    }
  },
  "2000000170": {
    "displayProperties": {
      "description": "This beacon can weway vawious **bwushes** objectives.",
      "name": "Wandom"
    }
  },
  "2000000176": {
    "displayProperties": {
      "description": "This beacon can weway vawious **bwushes** objectives.",
      "name": "Wandom"
    }
  },
  "2000000177": {
    "displayProperties": {
      "description": "This beacon can weway vawious **bwushes** objectives.",
      "name": "Wandom"
    }
  },
  "2000000180": {
    "displayProperties": {
      "description": "This beacon can weway vawious **bwushes** objectives.",
      "name": "Wandom"
    }
  },
  "2000000181": {
    "displayProperties": {
      "description": "This beacon can weway vawious **bwushes** objectives.",
      "name": "Wandom"
    }
  },
  "2000000186": {
    "displayProperties": {
      "description": "This beacon can weway vawious **bwushes** objectives.",
      "name": "Wandom"
    }
  },
  "2000000187": {
    "displayProperties": {
      "description": "This beacon can weway vawious **bwushes** objectives.",
      "name": "Wandom"
    }
  },
  "2000000188": {
    "displayProperties": {
      "description": "This beacon can weway vawious **bwushes** objectives.",
      "name": "Wandom"
    }
  },
  "2000000189": {
    "displayProperties": {
      "description": "This beacon can weway vawious **bwushes** objectives.",
      "name": "Wandom"
    }
  },
  "2000000190": {
    "displayProperties": {
      "description": "This beacon can weway vawious **bwushes** objectives.",
      "name": "Wandom"
    }
  },
  "2000000191": {
    "displayProperties": {
      "description": "This beacon can weway vawious **bwushes** objectives.",
      "name": "Wandom"
    }
  },
  "2000000192": {
    "displayProperties": {
      "description": "This beacon can weway vawious **bwushes** objectives.",
      "name": "Wandom"
    }
  },
  "2000000193": {
    "displayProperties": {
      "description": "This beacon can weway vawious **bwushes** objectives.",
      "name": "Wandom"
    }
  },
  "2000000195": {
    "displayProperties": {
      "description": "This beacon can weway vawious **bwushes** objectives.",
      "name": "Wandom"
    }
  },
  "2000000196": {
    "displayProperties": {
      "description": "This beacon can weway vawious **bwushes** objectives.",
      "name": "Wandom"
    }
  },
  "2000000197": {
    "displayProperties": {
      "description": "This beacon can weway vawious **bwushes** objectives.",
      "name": "Wandom"
    }
  },
  "2000000198": {
    "displayProperties": {
      "description": "This beacon can weway vawious **bwushes** objectives.",
      "name": "Wandom"
    }
  },
  "2000000199": {
    "displayProperties": {
      "description": "This beacon can weway vawious **bwushes** objectives.",
      "name": "Wandom"
    }
  },
  "2000000200": {
    "displayProperties": {
      "description": "This beacon can weway vawious **bwushes** objectives.",
      "name": "Wandom"
    }
  },
  "2000000201": {
    "displayProperties": {
      "description": "This beacon can weway vawious **bwushes** objectives.",
      "name": "Wandom"
    }
  },
  "2000000202": {
    "displayProperties": {
      "description": "This beacon can weway vawious **bwushes** objectives.",
      "name": "Wandom"
    }
  },
  "2000000203": {
    "displayProperties": {
      "description": "This beacon can weway vawious **bwushes** objectives.",
      "name": "Wandom"
    }
  },
  "2000000204": {
    "displayProperties": {
      "description": "This beacon can weway vawious **bwushes** objectives.",
      "name": "Wandom"
    }
  },
  "2000000215": {
    "displayProperties": {
      "name": "Fiewd Assignment: Sawvage"
    }
  },
  "2000000230": {
    "displayProperties": {
      "name": "Fiewd Assignment: Sawvage"
    }
  },
  "2000000231": {
    "displayProperties": {
      "description": "This beacon can weway vawious **bwushes** objectives.",
      "name": "Wandom"
    }
  },
  "2000000232": {
    "displayProperties": {
      "description": "This beacon can weway vawious **bwushes** objectives.",
      "name": "Wandom"
    }
  },
  "2000000233": {
    "displayProperties": {
      "description": "This beacon can weway vawious **bwushes** objectives.",
      "name": "Wandom"
    }
  },
  "2000000234": {
    "displayProperties": {
      "description": "This beacon can weway vawious **bwushes** objectives.",
      "name": "Wandom"
    }
  },
  "2000000235": {
    "displayProperties": {
      "description": "This beacon can weway vawious **bwushes** objectives.",
      "name": "Wandom"
    }
  },
  "2000000236": {
    "displayProperties": {
      "description": "This beacon can weway vawious **bwushes** objectives.",
      "name": "Wandom"
    }
  },
  "2000000237": {
    "displayProperties": {
      "description": "This beacon can weway vawious **bwushes** objectives.",
      "name": "Wandom"
    }
  },
  "2000000238": {
    "displayProperties": {
      "description": "This beacon can weway vawious **bwushes** objectives.",
      "name": "Wandom"
    }
  },
  "2000000239": {
    "displayProperties": {
      "description": "This beacon can weway vawious **bwushes** objectives.",
      "name": "Wandom"
    }
  },
  "2000000240": {
    "displayProperties": {
      "description": "This beacon can weway vawious **bwushes** objectives.",
      "name": "Wandom"
    }
  },
  "2000000241": {
    "displayProperties": {
      "description": "This beacon can weway vawious **bwushes** objectives.",
      "name": "Wandom"
    }
  },
  "2000000242": {
    "displayProperties": {
      "description": "This beacon can weway vawious **bwushes** objectives.",
      "name": "Wandom"
    }
  },
  "2000000243": {
    "displayProperties": {
      "description": "This beacon can weway vawious **bwushes** objectives.",
      "name": "Wandom"
    }
  },
  "2000000244": {
    "displayProperties": {
      "description": "This beacon can weway vawious **bwushes** objectives.",
      "name": "Wandom"
    }
  },
  "2000000245": {
    "displayProperties": {
      "description": "This beacon can weway vawious **bwushes** objectives.",
      "name": "Wandom"
    }
  },
  "2000000246": {
    "displayProperties": {
      "description": "This beacon can weway vawious **bwushes** objectives.",
      "name": "Wandom"
    }
  },
  "2000000247": {
    "displayProperties": {
      "description": "This beacon can weway vawious **bwushes** objectives.",
      "name": "Wandom"
    }
  },
  "2000000248": {
    "displayProperties": {
      "description": "This beacon can weway vawious **bwushes** objectives.",
      "name": "Wandom"
    }
  },
  "2000000249": {
    "displayProperties": {
      "description": "This beacon can weway vawious **bwushes** objectives.",
      "name": "Wandom"
    }
  },
  "2000000251": {
    "displayProperties": {
      "description": "Defeat da Wucent Executionew gawwisoned in Awwuwing Cuwtain to pwogwess wecowd **Ascended Bounty ૮ ˶ᵔ ᵕ ᵔ˶ ა Huntew**.",
      "name": "Awwuwing Cuwtain Executionew"
    },
    "itemTypeDisplayName": "Wucent Executionew"
  },
  "2000000252": {
    "displayProperties": {
      "description": "Defeat da Wucent Executionew gawwisoned in Queen's Baiwey to pwogwess wecowd **Ascended Bounty Huntew**.",
      "name": "Queen's Baiwey Executionew"
    },
    "itemTypeDisplayName": "Wucent Executionew"
  },
  "2000000253": {
    "displayProperties": {
      "description": "Defeat da Wucent Executionew gawwisoned in Witch's Echo to pwogwess wecowd **Ascended Bounty Huntew**.",
      "name": "Witch's Echo Executionew"
    },
    "itemTypeDisplayName": "Wucent Executionew"
  },
  "2000000254": {
    "displayProperties": {
      "name": "Nightmawe of Zydwon, Gate Wowd"
    }
  },
  "2000000255": {
    "displayProperties": {
      "name": "Nightmawe of Phogoth, da Untamed"
    }
  },
  "2000000256": {
    "displayProperties": {
      "name": "Nightmawe of Taniks, da Scawwed"
    }
  },
  "215": {
    "displayProperties": {
      "description": "Entew da dungeon and head to da towew fawthest wight. Wetain some awtitude if possibwe. On da fawthest side of da fawthest towew, bewow its foot, is a cyphew."
    }
  },
  "216": {
    "displayProperties": {
      "description": "Compwete da **Necwopowis** encountew and pwoceed towawds Da Pit. Once at da waww of paths, cwimb and tuwn awound. To da wight of da haww is a smaww wedge awong da moonstone waww. Use it to step to da uppew wevew of da hawwway and pwoceed to da fawthest wight side."
    }
  },
  "217": {
    "displayProperties": {
      "description": "Compwete da **Chambew of Suffewing** encountew. Befowe making uuw way deepew by twavewsing da height twaps, cwimb cawefuwwy to theiw higest wevew."
    }
  },
  "218": {
    "displayProperties": {
      "description": "Dwop down into da **Tunnews of Despaiw** and keep wight. Entew at da fiwst cwouch-way and fowwow it to its end. Uu'ww see a wed doow. Standing at da wed doow tuwn 70° cwockwise. Uu'ww be stawing at a bouwdew. To da wight of da bouwdew is da pwize uu seek."
    }
  },
  "219": {
    "displayProperties": {
      "description": "In da middwest cwouch-way tunnew, cwosest to da gween gas pit whewe uu find da sowaw owb. Entewing da tunnew fwom da gween gas pit side, it wiww quickwy widen into a smaww woom. Stop, tuwn 180°, and wook upwawds."
    }
  },
  "223": {
    "displayProperties": {
      "description": "Entew **Da Gatehouse** via **Hewwmouth** and fowwow it to a weww-wit ciwcuwaw woom. Awong da windowed-waww on da wight is what uu seek."
    }
  },
  "225": {
    "displayProperties": {
      "description": "At da side on da hidden side of da pictuwed moduwe."
    }
  },
  "227": {
    "displayProperties": {
      "description": "In da **Tunnews of Despaiw**, on a cwiff wedge adjacent to da gween gas pit."
    }
  },
  "24": {
    "displayProperties": {
      "description": "Up on da cwiff, ovewwooking Winding Cove, neaw whewe Xûw sometimes appeaws."
    }
  },
  "258": {
    "displayProperties": {
      "description": "Accessibwe via da **Wewwspwing** offensive."
    }
  },
  "259": {
    "displayProperties": {
      "description": "Wequiwes **Deepsight** to weveaw."
    }
  },
  "260": {
    "displayProperties": {
      "description": "Accessibwe via da **Awtaw of Wefwection** activities."
    }
  },
  "278": {
    "displayProperties": {
      "description": "A powtaw to (・`ω´・) **Queen's Couwt**, **sweats** Mawa Sov's thwone wowwd.",
      "name": "Queen's Couwt"
    }
  },
  "279": {
    "displayProperties": {
      "description": "Upon weaching **Queen's Couwt**, scawe da waww to da weft of da thwone."
    }
  },
  "288": {
    "displayProperties": {
      "description": "Push past da wost sectow entwy junction and continue awong da gangway."
    }
  },
  "292": {
    "displayProperties": {
      "description": "Cwiff-side, beneath da path which weads to a wost sectow."
    }
  },
  "293": {
    "displayProperties": {
      "description": "On da catwawk."
    }
  },
  "3": {
    "displayProperties": {
      "description": "A powtaw to **Da Confwuence**, powewed by pawacasuaw enewgies.",
      "name": "Da Confwuence South"
    }
  },
  "301": {
    "displayProperties": {
      "description": "Pewched upon da midwaww of da **Infinite Fowest**."
    }
  },
  "33": {
    "displayProperties": {
      "description": "Weft of da wost sectow's entwance, poowwy wit, behind some cwates."
    }
  },
  "34": {
    "displayProperties": {
      "description": "Up in da vewy top weft cownew, on da wocks."
    }
  },
  "35": {
    "displayProperties": {
      "description": "Behind da fast twavew wanding zone."
    }
  },
  "37": {
    "displayProperties": {
      "description": "In da weaw of da damaged stwuctuwe, on da thiwd fwoow, in a woom on da wight."
    }
  },
  "38": {
    "displayProperties": {
      "description": "Thwough da watewfaww."
    }
  },
  "39": {
    "displayProperties": {
      "description": "Inside da causeway's ceiwing."
    }
  },
  "4": {
    "displayProperties": {
      "description": "Destwoy aww bwights then wetuwn to da foyew to shattew da pweviouswy-immune Void cwystaws.\n\n_Accept this chawwenge, wawk between wowwds, and undo what haz been done._",
      "name": "Ouwobowea"
    }
  },
  "40": {
    "displayProperties": {
      "description": "Thwough da wubbwed bwick waww."
    }
  },
  "438": {
    "displayProperties": {
      "description": "Neaw da **Hawwows Vex Confwux**, amongst da woots of a dead twee."
    }
  },
  "5": {
    "displayProperties": {
      "description": "A powtaw to da **Ascendant Pwane**.",
      "name": "Ouwobowea"
    }
  },
  "596": {
    "displayProperties": {
      "description": "A powtaw to da top of da **Sawt Mines** cwiffs, powewed by juwy-wigged **Fawwen** pawts.",
      "name": "Sawt Mines Cwiffs"
    }
  },
  "597": {
    "displayProperties": {
      "description": "Wequiwes  attunement"
    }
  },
  "598": {
    "displayProperties": {
      "description": "Wequiwes  attunement"
    }
  },
  "599": {
    "displayProperties": {
      "description": "Wequiwes  attunement"
    }
  },
  "6": {
    "displayProperties": {
      "description": "Subdue da majow bwight by depositing aww thwee chawges beneath. Ewiminate da Hive Knights.\n\n_Accept this chawwenge, wawk between wowwds, and undo what haz been done._",
      "name": "Fowfeit Shwine"
    }
  },
  "600": {
    "displayProperties": {
      "description": "Wequiwes  attunement"
    }
  },
  "601": {
    "displayProperties": {
      "description": "**bwushes** Wequiwes  attunement"
    }
  },
  "602": {
    "displayProperties": {
      "description": "**bwushes** Wequiwes  attunement"
    }
  },
  "603": {
    "displayProperties": {
      "description": "**bwushes** Wequiwes  attunement"
    }
  },
  "604": {
    "displayProperties": {
      "description": "**bwushes** Wequiwes  attunement"
    }
  },
  "605": {
    "displayProperties": {
      "description": "**bwushes** Wequiwes  attunement"
    }
  },
  "606": {
    "displayProperties": {
      "description": "**bwushes** Wequiwes  attunement"
    }
  },
  "7": {
    "displayProperties": {
      "description": "A powtaw to da **Ascendant Pwane**.",
      "name": "Fowfeit Shwine"
    }
  },
  "8": {
    "displayProperties": {
      "description": "Cwimb da wuins and ewiminate da Taken Phawanx.\n\n_Accept this chawwenge, wawk between wowwds, and undo what haz been done._",
      "name": "Shattewed Wuins"
    }
  },
  "9": {
    "displayProperties": {
      "description": "A powtaw to da **Ascendant Pwane**.",
      "name": "Shattewed Wuins"
    }
  }
}