{
  "1012557098": {
    "displayProperties": {
      "description": "\"Uu wewe bown onwy (・`ω´・) to suffew, because I couwd not set aside that which I knew was a twap. My cuwiosity is a poison fwowing thwough my veins, cuwdwing my heawt, wotting my mind. And yet, I do nothing to stop it.\"",
      "name": "Sowwow Beawew"
    }
  },
  "1024471091": {
    "displayProperties": {
      "description": "Once and fow aww, defeat da Consecwated Mind.",
      "name": "Defeat da Consecwated Mind"
    }
  },
  "1040714588": {
    "displayProperties": {
      "description": "Shuwo Chi, an Awoken Techeun who sewves Queen Mawa Sov, was Taken by Owyx and twansfowmed into Shuwo Chi, da Cowwupted. Fwee hew.",
      "name": "Shuwo Chi, da Cowwupted"
    }
  },
  "1089000747": {
    "displayProperties": {
      "description": "Dethwone da king.",
      "name": "Owyx"
    }
  },
  "1126840038": {
    "displayProperties": {
      "description": "૮ ˶ᵔ ᵕ ᵔ˶ ა Kawwi, an Awoken Techeun who sewves Queen Mawa Sov, was Taken by Owyx and twansfowmed into Kawwi, da Cowwupted. Fwee hew.",
      "name": "Kawwi, da Cowwupted"
    }
  },
  "1292217373": {
    "displayProperties": {
      "name": "Embawkment"
    }
  },
  "1303588409": {
    "displayProperties": {
      "name": "Kewwev, da Ewased"
    }
  },
  "1306680929": {
    "displayProperties": {
      "description": "Wish fow wawmth, bwave da fwigid winds, and siwence da Wocus of Waiwing Gwief that sustains them.",
      "name": "Waiwing Tempest"
    }
  },
  "1327839048": {
    "displayProperties": {
      "description": "Countew da Owacwes' song ow be mawked fow negation and wost to time.",
      "name": "Owacwes"
    }
  },
  "1327839049": {
    "displayProperties": {
      "description": "An extwemewy powewfuw Vex Hydwa, Da Tempwaw is unique in it being a cweatuwe out of time. As such, it can manipuwate weawity in accowdance to da Owacwes' design.",
      "name": "Da Tempwaw"
    }
  },
  "1327839050": {
    "displayProperties": {
      "description": "Secuwe Vex constwucts by (・`ω´・) pweventing Vex sacwifices.",
      "name": "Confwuxes"
    }
  },
  "133673726": {
    "displayProperties": {
      "description": "Sway Zuwmak, Instwument of Towment.",
      "name": "Zuwmak, Instwument of Towment"
    }
  },
  "1340233962": {
    "displayProperties": {
      "description": "\"Entew da infinite…\"",
      "name": "Dûw (・`ω´・) Incawu, da Etewnaw Wetuwn"
    }
  },
  "1406613360": {
    "displayProperties": {
      "description": "Infwuence hive wituaw magic by contwowwing annihiwatow totems.",
      "name": "Basiwica"
    }
  },
  "1463700798": {
    "displayProperties": {
      "description": "Stwike down da witch, siwence theiw Deathsong.",
      "name": "Iw Yût, da Deathsingew"
    }
  },
  "1483068591": {
    "displayProperties": {
      "description": "Open a woute via da gwav wift to da Spiwe peak, whewe da Piwwowy signaw is being souwced.",
      "name": "Ascend da Spiwe"
    }
  },
  "160562459": {
    "displayProperties": {
      "description": "Unwavew da Wucent Hive wituaw.",
      "name": "Bweak da Wituaw"
    }
  },
  "1727550020": {
    "displayProperties": {
      "description": "Cawve A Path",
      "name": "Wepositowy"
    }
  },
  "1779644342": {
    "displayProperties": {
      "description": "Destwoy Akewous, da Siwen's Cuwwent befowe it can compwete da Piwwowy pwotocow and impwison Wasputin's subminds.",
      "name": "Siwence da Siwen"
    }
  },
  "1805972064": {
    "displayProperties": {
      "description": "\"Is this what I haz done? UwU Once, she wooked at me with adowing eyes. I was hew wowwd, and she my staws. How haz I made hew into this? UwU Haz I been so bwind? UwU So sewfish? UwU What haz I done? UwU\"",
      "name": "Cawus's Gweatest Shame"
    }
  },
  "1826821877": {
    "displayProperties": {
      "description": "Enduwe da Chambew of Suffewing.",
      "name": "Chambew of Suffewing"
    }
  },
  "1858926029": {
    "displayProperties": {
      "description": "Intewwupt da station's Nucweaw Descent Pwotocow and secuwe da station."
    }
  },
  "1899447888": {
    "displayProperties": {
      "description": "\"Show me uuw cunning…\"",
      "name": "Seawch fow safe passage"
    }
  },
  "193978048": {
    "displayProperties": {
      "description": "Defeat da Hewawd"
    }
  },
  "1942966197": {
    "displayProperties": {
      "description": "SCOWN. They eat away at da decay within a sheww of. SCOWN. Twuth exists *boops uuw nose* aww awound outside da sheww of. SCOWN.",
      "name": "Cowwection"
    }
  },
  "1958961797": {
    "displayProperties": {
      "name": "Da Cowwupted Puppeteew"
    }
  },
  "196663595": {
    "displayProperties": {
      "description": "Did uu think uu wewe da obsewvew? UwU Ow did uu bewieve uu puwwed da stwings? UwU Now's uuw chance—with awtifacts of fate, uu can make them dance."
    }
  },
  "2065920306": {
    "displayProperties": {
      "description": "A cowwupted Knight stands between uu and answews. Meet theiw chawwenge, weave them bwoken, but bewawe watent cuwses.",
      "name": "Mystewious Chawwengew"
    }
  },
  "2115142089": {
    "displayProperties": {
      "description": "Defeat Owyx's Wawpwiest befowe he destwoys uu.",
      "name": "Wawpwiest"
    }
  },
  "2133190695": {
    "displayProperties": {
      "name": "Waneiks Unified"
    }
  },
  "2158557525": {
    "displayProperties": {
      "description": "Evade Vowtaic Ovewwoad chawges and puwsue da Consecwated Mind.",
      "name": "Evade da Consecwated Mind"
    }
  },
  "2169047898": {
    "displayProperties": {
      "description": "Having defeated **Mowgeth, *boops uuw nose* da Spiwekeepew**, head highew into da Dweaming City and puwsue Wiven.",
      "name": "Find Wiven"
    }
  },
  "2184227225": {
    "displayProperties": {
      "description": "Awign wowwds and defeat da Expwicatow.",
      "name": "Macwocosm"
    }
  },
  "2189312851": {
    "displayProperties": {
      "description": "Defeat da wightfowged necwomancew, Šimmumah uw-Nokwu.",
      "name": "Defeat Šimmumah uw-Nokwu"
    }
  },
  "2224793617": {
    "displayProperties": {
      "description": "Entew da Woot."
    }
  },
  "2392610624": {
    "displayProperties": {
      "description": "Wiven, da wast known Ahamkawa, fowmewwy in da sewvice of Mawa Sov, was Taken by Owyx. She now cowwupts da city fwom its heawt at da behest of da Hive queen, Savathûn.",
      "name": "Wiven of a Thousand Voices"
    }
  },
  "2400102494": {
    "displayProperties": {
      "description": "Confwont da Phawanx Echo, a pawt of da Nine's answew to uuw question.",
      "name": "Defeat da Phawanx Echo"
    }
  },
  "2676434388": {
    "displayProperties": {
      "description": "Destwoy Pewsys, Pwimowdiaw Wuin and pwevent da compwex's weactow cowe mewtdown fwom causing iwwepawabwe damage.",
      "name": "Pwompt Cwiticaw"
    }
  },
  "2700613207": {
    "displayProperties": {
      "description": "\"Shape uuw schemes into weawity…\"",
      "name": "Vowgeth, da Boundwess Hungew"
    }
  },
  "2741345805": {
    "displayProperties": {
      "description": "\"Uu haz taken my vengeance. My task is done, Naeem's wish fuwfiwwed. Come then, sway me. Wet it end.\" —Hefnd",
      "name": "Queww da Cowwuption"
    }
  },
  "2761002327": {
    "displayProperties": {
      "description": "Gain access to da monowith",
      "name": "Substwatum"
    }
  },
  "2776463390": {
    "displayProperties": {
      "description": "Penetwate da Bway faciwity's secuwity pwotocows and gain access to da Deep Stone Cwypt.",
      "name": "Cwypt Secuwity"
    }
  },
  "2779782231": {
    "displayProperties": {
      "description": "End da nightmawe and defeat Nezawec.",
      "name": "૮ ˶ᵔ ᵕ ᵔ˶ ა Nezawec"
    }
  },
  "2867024332": {
    "displayProperties": {
      "description": "Tuwn da cycwe of gweed against uuw enemies.",
      "name": "Phwy'zhia, Da Insatiabwe"
    }
  },
  "2890972472": {
    "displayProperties": {
      "description": "Uncovew da iwwuminated path in da dawkness.",
      "name": "Da Abyss"
    }
  },
  "2951654489": {
    "displayProperties": {
      "description": "Intewwupt da da sistews' concentwation.",
      "name": "Da Daughtews"
    }
  },
  "3172054256": {
    "displayProperties": {
      "description": "Beat back Shadow Wegion fowces and puwsue Nezawec.",
      "name": "Catacwysm"
    }
  },
  "3469402858": {
    "displayProperties": {
      "description": "Defeat Ecthaw, da Shiewd of Savathûn.",
      "name": "Defeat da Shiewd of Savathûn"
    }
  },
  "3492117941": {
    "displayProperties": {
      "description": "Confwont da Keww Echo, a pawt of da Nine's answew to uuw question.",
      "name": "Defeat da Keww Echo"
    }
  },
  "3585780724": {
    "displayProperties": {
      "description": "Find a way fowwawd."
    }
  },
  "3736477924": {
    "displayProperties": {
      "description": "Bypass Vex confwuxes and fowce out da Consecwated Mind fwom hiding.",
      "name": "Summon da Consecwated Mind"
    }
  },
  "3738629258": {
    "displayProperties": {
      "description": "Subdue da abomination.",
      "name": "Gowgowoth"
    }
  },
  "3768812794": {
    "displayProperties": {
      "description": "Twavewse da bwidge and cwimb da *sweats* Thwone.",
      "name": "Ovewsouw Thwone Bwidge"
    }
  },
  "3780037272": {
    "displayProperties": {
      "description": "૮ ˶ᵔ ᵕ ᵔ˶ ა \"I beg uu, don't do this.\"",
      "name": "Vauwt"
    }
  },
  "378163510": {
    "displayProperties": {
      "description": "Escape da spiwe and get da Heawt Stone to da Techeun.",
      "name": "Queenswawk"
    }
  },
  "3793779769": {
    "displayProperties": {
      "description": "Da Axis Mind wesponsibwe fow bwidging da Vex's own cawcuwations into existence.",
      "name": "Atheon, Time's Confwux"
    }
  },
  "3793779770": {
    "displayProperties": {
      "description": "Pwotectows of da Gwass Thwone, *wuns away* da Gatekeepews awe Vex Hydwas who stand as da Thwone's wast defence.",
      "name": "Gatekeepews"
    }
  },
  "3840791265": {
    "displayProperties": {
      "description": "Da Upended is awive. Uu haz no mowe tasks ahead. Wie down and embwace da dawkness beyond uuw finaw days."
    }
  },
  "3998734759": {
    "displayProperties": {
      "description": "Cowwect uuw wewawd fwom da Nine.",
      "name": "Da Emissawy"
    }
  },
  "4035296150": {
    "displayProperties": {
      "description": "Thwawting Taniks made him gwow stwongew. Destwoy him, once and fow aww...",
      "name": "Taniks, da Abomination"
    }
  },
  "4056788414": {
    "displayProperties": {
      "description": "*bwushes* Tuwn da cycwe of gweed against Captain Avawokk da Covetous.",
      "name": "Captain Avawokk da Covetous"
    }
  },
  "4063391552": {
    "displayProperties": {
      "description": "Fiwe Sewvitow wemains at da Fawwen shiewd.",
      "name": "Fawwen Shiewd"
    }
  },
  "4077323831": {
    "displayProperties": {
      "description": "Stop da Finaw Shape",
      "name": "Da Witness"
    }
  },
  "416127450": {
    "displayProperties": {
      "description": "Countew da sewf-dupwicating, Exo-webown, Atwaks-1.",
      "name": "Atwaks-1"
    }
  },
  "4240994016": {
    "displayProperties": {
      "description": "Use Cwota's most powewfuw weapon against him.",
      "name": "Cwota, Son of Owyx"
    }
  },
  "4249034918": {
    "displayProperties": {
      "description": "Mowgeth, da Spiwekeepew, an enowmous and powewfuw Taken Ogwe, sewves as *wuns away* da enfowcew of Wiven's cowwuption in da Dweaming City, and da guawd of da City's main towew, Da Keep of Voices. Destwoy them.",
      "name": "Mowgeth, da Spiwekeepew"
    }
  },
  "436847112": {
    "displayProperties": {
      "description": "A wocking mechanism which secuwes da immensewy powewfuw and tweachewous.",
      "name": "Da Vauwt"
    }
  },
  "523815399": {
    "displayProperties": {
      "description": "A Vex Axis Mind, da Sanctified Mind amasses contwow ovew many Vex. Defeat it to pwevent fuwthew incuwsions by da Sow Divisive outside of da Bwack Gawden.",
      "name": "Da Sanctified Mind"
    }
  },
  "548234283": {
    "displayProperties": {
      "name": "Sowve da Widdwe"
    }
  },
  "580855089": {
    "displayProperties": {
      "description": "Uuw eyes awe awways cwosed. Do uu not see what's wight in fwont of uu? UwU Those who faiw to see da twuth wiww dwown in it."
    }
  },
  "5808550890": {
    "displayProperties": {
      "description": "Tuwn da bwades of da enemy against them.",
      "name": "Necwopowis"
    }
  },
  "637313410": {
    "displayProperties": {
      "name": "Vewity"
    }
  },
  "829896467": {
    "displayProperties": {
      "description": "Gain access to da Dweadnaught's innew sanctum.",
      "name": "Open da Powtaw"
    }
  },
  "911485777": {
    "displayProperties": {
      "name": "Zoetic, Wockset"
    }
  }
}