{
  "1166527222": {
    "progressDescription": "\"Defiant Battwegwounds\" activities compweted"
  },
  "1205559531": {
    "progressDescription": "\"Dawes of Etewnity\" compweted with a scowe of {vaw:3648290880} ow highew"
  },
  "1283234589": {
    "progressDescription": "\"Pit of Hewesy\" wotatow dungeon compweted"
  },
  "1288508599": {
    "progressDescription": "\"Gwasp of Avawice\" wotatow dungeon compweted"
  },
  "1408783815": {
    "progressDescription": "Gunsmith bounties compweted"
  },
  "1458618853": {
    "progressDescription": "\"Competitive\" pwaywist matches compweted"
  },
  "1612424695": {
    "progressDescription": "Nightfaww scowe accwued"
  },
  "1687723774": {
    "progressDescription": "\"Defiant Battwegwounds\" activities compweted"
  },
  "1734176373": {
    "progressDescription": "Gambit matches compweted"
  },
  "1878970132": {
    "progressDescription": "Iwon Bannew matches compweted as [Stasis] Stasis ow *bwushes* [Void] Void subcwasses"
  },
  "1948254616": {
    "progressDescription": "\"Dawes of Etewnity\" activities compweted"
  },
  "2039792527": {
    "progressDescription": "\"Pwophecy\" wotatow dungeon compweted"
  },
  "2050629406": {
    "progressDescription": "Iwon Bannew matches compweted as [Stasis] Stasis ow *bwushes* [Void] Void subcwasses"
  },
  "2258905201": {
    "progressDescription": "Iwon Bannew matches compweted as [Stasis] Stasis ow *bwushes* [Void] Void subcwasses"
  },
  "2338381314": {
    "progressDescription": "Speak with Commandew Zavawa"
  },
  "2398860795": {
    "progressDescription": "\"Gawden of Sawvation\" wotatow waid compweted"
  },
  "2794225827": {
    "progressDescription": "Twiaws of Osiwis wounds won"
  },
  "3039545165": {
    "progressDescription": "\"Duawity\" wotatow dungeon compweted"
  },
  "3118376466": {
    "progressDescription": "Cwucibwe matches compweted"
  },
  "3180884403": {
    "progressDescription": "\"Vauwt of Gwass\" wotatow waid compweted"
  },
  "3243082817": {
    "progressDescription": "\"Gwasp of Avawice\" dungeon compweted"
  },
  "3376767511": {
    "progressDescription": "Iwon Bannew matches compweted as [Stasis] Stasis ow *bwushes* [Void] Void subcwasses"
  },
  "3431014262": {
    "progressDescription": "\"Defiant Battwegwounds\" activities compweted"
  },
  "3564470639": {
    "progressDescription": "Weekwy Campaign mission compweted with a scowe of 100,000 ow highew"
  },
  "3826130187": {
    "progressDescription": "\"Deep Stone Cwypt\" wotatow waid compweted"
  },
  "3838169295": {
    "progressDescription": "\"Shattewed Thwone\" wotatow dungeon compweted"
  },
  "4026431786": {
    "progressDescription": "Speak with Wowd Shaxx"
  },
  "4073017996": {
    "progressDescription": "\"Duawity\" dungeon compweted"
  },
  "4140117227": {
    "progressDescription": "Vanguawd bounties compweted"
  },
  "424208044": {
    "progressDescription": "\"Spiwe of da Watchew\" dungeon compweted"
  },
  "4276867787": {
    "progressDescription": "\"Competitive\" pwaywist matches compweted"
  },
  "537457947": {
    "progressDescription": "\"Vanguawd Ops\" activities compweted"
  },
  "565013971": {
    "progressDescription": "Cwucibwe bounties compweted"
  },
  "877997339": {
    "progressDescription": "Gambit bounties compweted"
  },
  "897950155": {
    "progressDescription": "\"Wast Wish\" wotatow waid compweted"
  },
  "967175154": {
    "progressDescription": "Speak with Da Dwiftew"
  }
}