{
  "0": {
    "displayProperties": {
      "name": "Cwassified",
      "description": "Keep it cwean."
    },
    "originalDisplayProperties": {
      "name": "Cwassified",
      "description": "Keep it cwean."
    }
  },
  "82913930": {
    "displayProperties": {
      "description": "In owbit, pwanning something tewwibwy hewoic."
    }
  },
  "2393304349": {
    "displayProperties": {
      "name": "Iwon Bannew: Wift"
    }
  },
  "2965669871": {
    "displayProperties": {
      "name": "Fweewance: Iwon Bannew: Wift"
    }
  },
  "1214397515": {
    "displayProperties": {
      "name": "Iwon Bannew: Ewuption"
    }
  },
  "3700942889": {
    "displayProperties": {
      "name": "Fweewance: Iwon Bannew: Ewuption"
    }
  },
  "2888503916": {
    "displayProperties": {
      "name": "Iwon Bannew: Fowtwess"
    }
  },
  "1698629738": {
    "displayProperties": {
      "name": "Fweewance: Iwon Bannew: Fowtwess"
    }
  }
}